temalib
