Metadata-Version: 2.1
Name: temalib
Version: 3.1.0
Summary: a library that was made for some ammeter bullshuy
Home-page: 
Author: tema5002
Author-email: xtema5002x@gmail.com
License: MIT
Keywords: bullshuy
Classifier: Development Status :: 5 - Production/Stable
Classifier: Intended Audience :: Education
Classifier: Operating System :: Microsoft :: Windows :: Windows 11
Classifier: License :: OSI Approved :: MIT License
Classifier: Programming Language :: Python :: 3
License-File: LICENSE.txt
